{
  "event": "第一回横浜観艦式予行 甲種(ほうせん)",
  "date": "2014-08-03",
  "prefecture": "神奈川",
  "venues": "パシフィコ横浜",
  "setlist": {
    "main": [
      [
        "佐倉綾音",
        [
          "華の二水戦",
          "恋の2-4-11"
        ]
      ],
      [
        "洲崎綾",
        [
          "鎮守府の朝"
        ]
      ],
      [
        "藤田咲/野水伊織",
        [
          "暁の水平線に"
        ]
      ],
      [
        "東山奈央",
        [
          "提督との絆"
        ]
      ]
    ],
    "encore": [
      [
        "全員",
        [
          "提督との絆"
        ]
      ]
    ]
  }
}
