{
  "event": "ANIMAX MUSIX 2015 YOKOHAMA",
  "date": "2015-11-21",
  "prefecture": "神奈川",
  "venues": "横浜アリーナ",
  "setlist": {
    "main": [
      [
        "AKINO with bless4",
        [
          "エクストラ・マジック・アワー",
          "海色",
          "創聖のアクエリオン"
        ]
      ],
      [
        "綾野ましろ",
        [
          "vanilla sky",
          "ideal white"
        ]
      ],
      [
        "茅原実里",
        [
          "black bullet"
        ]
      ],
      [
        "川田まみ",
        [
          "ebb and flow"
        ]
      ],
      [
        "大橋彩香",
        [
          "YES!!",
          "おしえてブルースカイ"
        ]
      ],
      [
        "西沢幸奏",
        [
          "吹雪",
          "Brand-new World"
        ]
      ],
      [
        "marina",
        [
          "Crow Song",
          "Trigger"
        ]
      ],
      [
        "内田真礼",
        [
          "楽園まで"
        ]
      ],
      [
        "小野賢章",
        [
          "FANTASTIC TUNE",
          "ZERO"
        ]
      ],
      [
        "i☆Ris",
        [
          "NEXTAGE",
          "ブライトファンタジー"
        ]
      ],
      [
        "Gero",
        [
          "BELOVED×SURVIVAL",
          "DREAMER"
        ]
      ],
      [
        "May'n/茅原実里",
        [
          "シュガーソングとビターステップ"
        ]
      ],
      [
        "内田真礼/上坂すみれ",
        [
          "Sparkling Daydream"
        ]
      ],
      [
        "西沢幸奏",
        [
          "未来形Answer"
        ]
      ],
      [
        "marina",
        [
          "Allegro Cantabile"
        ]
      ],
      [
        "大橋彩香",
        [
          "桜キッス"
        ]
      ],
      [
        "南條愛乃",
        [
          "プラチナ"
        ]
      ],
      [
        "南條愛乃/西沢幸奏/大橋彩香/marina",
        [
          "光と影を抱きしめたまま"
        ]
      ],
      [
        "OxT",
        [
          "Clattanoia",
          "STRIDER'S HIGH",
          "君じゃなきゃダメみたい"
        ]
      ],
      [
        "川田まみ",
        [
          "PSI-missing",
          "masterpiece",
          "See visionS",
          "No buts!",
          "Gardens"
        ]
      ],
      [
        "ALTIMA",
        [
          "CYBER CYBER",
          "Burst The Gravity"
        ]
      ],
      [
        "KOTOKO/ALTIMA",
        [
          "PLASMIC FIRE",
          "→unfinished→"
        ]
      ],
      [
        "Gero",
        [
          "RIMFIRE"
        ]
      ],
      [
        "小野賢章",
        [
          "ペガサス幻想"
        ]
      ],
      [
        "OxT",
        [
          "ロマンティックあげるよ"
        ]
      ],
      [
        "内田真礼",
        [
          "からっぽカプセル",
          "世界が形失くしても"
        ]
      ],
      [
        "上坂すみれ",
        [
          "Inner Urge",
          "げんし、女子は、たいようだった。"
        ]
      ],
      [
        "岸田教団 & THE明星ロケッツ",
        [
          "HIGHSCHOOL OF THE DEAD",
          "ストライク・ザ・ブラッド",
          "GATE～それは暁のように～"
        ]
      ],
      [
        "ichigo(岸田教団&THE明星ロケッツ)",
        [
          "バリバリ最強NO.1"
        ]
      ],
      [
        "綾野ましろ",
        [
          "Reason"
        ]
      ],
      [
        "May'n",
        [
          "Hello,world!"
        ]
      ],
      [
        "OxT/AKINO with bless4",
        [
          "Vanguard"
        ]
      ],
      [
        "Gero/i☆Ris",
        [
          "かくしん的☆めたまるふぉ～ぜっ!"
        ]
      ],
      [
        "川田まみ/KOTOKO",
        [
          "緋色の空",
          "being",
          "I'll believe",
          "Light My Fire",
          "JOINT"
        ]
      ],
      [
        "南條愛乃",
        [
          "黄昏のスタアライト",
          "君が笑む夕暮れ",
          "きみを探しに"
        ]
      ],
      [
        "茅原実里",
        [
          "境界の彼方",
          "恋",
          "Paradise Lost",
          "SELF PRODUCER"
        ]
      ],
      [
        "May'n",
        [
          "Scarlet Ballet",
          "ヤマイダレdarlin'",
          "Chase the world",
          "夜明けのロゴス"
        ]
      ],
      [
        "全員",
        [
          "Butter-Fly～tri.Version～"
        ]
      ]
    ]
  }
}
